mazelib/__init__.py
mazelib/mazelib.py
mazelib/generate/BacktrackingGenerator.py
mazelib/generate/DungeonRooms.py
mazelib/generate/AldousBroder.cpython-39-x86_64-linux-gnu.so
mazelib/generate/Ellers.pxd
mazelib/generate/__init__.py
mazelib/generate/Sidewinder.cpython-39-x86_64-linux-gnu.so
mazelib/generate/AldousBroder.py
mazelib/generate/Sidewinder.py
mazelib/generate/Division.pxd
mazelib/generate/Kruskal.py
mazelib/generate/HuntAndKill.cpython-39-x86_64-linux-gnu.so
mazelib/generate/DungeonRooms.pxd
mazelib/generate/DungeonRooms.cpython-39-x86_64-linux-gnu.so
mazelib/generate/BinaryTree.pxd
mazelib/generate/Division.cpython-39-x86_64-linux-gnu.so
mazelib/generate/CellularAutomaton.py
mazelib/generate/AldousBroder.pxd
mazelib/generate/HuntAndKill.pxd
mazelib/generate/GrowingTree.py
mazelib/generate/Ellers.py
mazelib/generate/TrivialMaze.py
mazelib/generate/GrowingTree.pxd
mazelib/generate/Prims.pxd
mazelib/generate/Division.py
mazelib/generate/MazeGenAlgo.cpython-39-x86_64-linux-gnu.so
mazelib/generate/TrivialMaze.cpython-39-x86_64-linux-gnu.so
mazelib/generate/Prims.py
mazelib/generate/TrivialMaze.pxd
mazelib/generate/Kruskal.pxd
mazelib/generate/Wilsons.pxd
mazelib/generate/MazeGenAlgo.py
mazelib/generate/Kruskal.cpython-39-x86_64-linux-gnu.so
mazelib/generate/MazeGenAlgo.pxd
mazelib/generate/Sidewinder.pxd
mazelib/generate/CellularAutomaton.pxd
mazelib/generate/Wilsons.cpython-39-x86_64-linux-gnu.so
mazelib/generate/Wilsons.py
mazelib/generate/BacktrackingGenerator.pxd
mazelib/generate/GrowingTree.cpython-39-x86_64-linux-gnu.so
mazelib/generate/HuntAndKill.py
mazelib/generate/Ellers.cpython-39-x86_64-linux-gnu.so
mazelib/generate/BacktrackingGenerator.cpython-39-x86_64-linux-gnu.so
mazelib/generate/Prims.cpython-39-x86_64-linux-gnu.so
mazelib/generate/BinaryTree.py
mazelib/generate/CellularAutomaton.cpython-39-x86_64-linux-gnu.so
mazelib/generate/BinaryTree.cpython-39-x86_64-linux-gnu.so
mazelib-0.9.14.dist-info/top_level.txt
mazelib-0.9.14.dist-info/WHEEL
mazelib-0.9.14.dist-info/LICENSE
mazelib-0.9.14.dist-info/METADATA
mazelib-0.9.14.dist-info/RECORD
