Metadata-Version: 2.1
Name: mazelib
Version: 0.9.14
Summary: A Python API for creating and solving mazes.
Home-page: https://github.com/john-science/mazelib
Author: John Stilley
License: MIT
Keywords: game mathematics algorithms maze mazes math games algorithm
Platform: any
Classifier: Development Status :: 4 - Beta
Classifier: Topic :: Software Development :: Libraries :: Python Modules
Classifier: Topic :: Scientific/Engineering :: Mathematics
Classifier: Topic :: Games/Entertainment :: Puzzle Games
Classifier: License :: OSI Approved :: MIT License
Classifier: Programming Language :: Python :: 3.4
Classifier: Programming Language :: Python :: 3.5
Classifier: Programming Language :: Python :: 3.6
Classifier: Programming Language :: Python :: 3.7
Classifier: Programming Language :: Python :: 3.8
Classifier: Programming Language :: Python :: 3.9
Classifier: Programming Language :: Python :: 3.10
Classifier: Programming Language :: Python :: 3.11
Classifier: Natural Language :: English
Requires-Python: >=3.4, <3.12
Requires-Dist: cython (<=0.29.32,>=0.27.0)
Requires-Dist: numpy (<=1.23.4,>=1.13.1)
